codeep-0.1.2.dist-info/licenses/LICENSE
codeep_upgrade/__init__.py
codeep_upgrade/main.py
codeep-0.1.2.dist-info/METADATA
codeep-0.1.2.dist-info/WHEEL
codeep-0.1.2.dist-info/top_level.txt
codeep-0.1.2.dist-info/RECORD
