Metadata-Version: 2.4
Name: codeep
Version: 0.1.2
Summary: A Python package for codeep upgrade optimization
Author-email: Codeep Team <andyxiaolei@gmail.com>
License-Expression: MIT
Project-URL: Homepage, https://github.com/codeepcc/codeep
Project-URL: Repository, https://github.com/codeepcc/codeep
Classifier: Development Status :: 3 - Alpha
Classifier: Intended Audience :: Developers
Classifier: Programming Language :: Python :: 3
Classifier: Programming Language :: Python :: 3.8
Classifier: Programming Language :: Python :: 3.9
Classifier: Programming Language :: Python :: 3.10
Classifier: Programming Language :: Python :: 3.11
Classifier: Operating System :: OS Independent
Requires-Python: >=3.8
License-File: LICENSE
Requires-Dist: requests>=2.20.0
Provides-Extra: dev
Requires-Dist: pytest>=6.0.0; extra == "dev"
Requires-Dist: black>=21.0.0; extra == "dev"
Requires-Dist: flake8>=3.8.0; extra == "dev"
Requires-Dist: mypy>=0.800; extra == "dev"
Dynamic: license-file
